LICENSE
MANIFEST.in
README.rst
setup.py
AdaptivePELE/__init__.py
AdaptivePELE/adaptiveSampling.py
AdaptivePELE/automateRoundsAdaptive.py
AdaptivePELE/makeRelease.py
AdaptivePELE/runAllTests.py
AdaptivePELE.egg-info/PKG-INFO
AdaptivePELE.egg-info/SOURCES.txt
AdaptivePELE.egg-info/dependency_links.txt
AdaptivePELE.egg-info/requires.txt
AdaptivePELE.egg-info/top_level.txt
AdaptivePELE/analysis/__init__.py
AdaptivePELE/analysis/addRejectedSteps.py
AdaptivePELE/analysis/analyse.py
AdaptivePELE/analysis/analyseClustering.py
AdaptivePELE/analysis/analysis_utils.py
AdaptivePELE/analysis/autoCorrelation.py
AdaptivePELE/analysis/backtrackAdaptiveTrajectory.py
AdaptivePELE/analysis/bestStructs.py
AdaptivePELE/analysis/calculateDistances.py
AdaptivePELE/analysis/calculateSASAvalues.py
AdaptivePELE/analysis/cluster.py
AdaptivePELE/analysis/clusterAdaptiveRun.py
AdaptivePELE/analysis/clusters_lagtime_grid.py
AdaptivePELE/analysis/compareClustering.py
AdaptivePELE/analysis/convertTrajectory.py
AdaptivePELE/analysis/correctRMSD.py
AdaptivePELE/analysis/count_clusters.py
AdaptivePELE/analysis/crossValidationClustering.py
AdaptivePELE/analysis/dehidratate_and_align.py
AdaptivePELE/analysis/extract_ligand_traj.py
AdaptivePELE/analysis/filter_by_radius.py
AdaptivePELE/analysis/findfirstbindingevent.py
AdaptivePELE/analysis/foldersFirstBindingEvent.py
AdaptivePELE/analysis/generateBox.py
AdaptivePELE/analysis/histCM.py
AdaptivePELE/analysis/identifyClusterSnapshot.py
AdaptivePELE/analysis/interactivePlot.py
AdaptivePELE/analysis/makePNGs.py
AdaptivePELE/analysis/makeRMSDClustering.py
AdaptivePELE/analysis/networkCM.py
AdaptivePELE/analysis/numberOfClusters.py
AdaptivePELE/analysis/pathwayRMSD.py
AdaptivePELE/analysis/plot3DNetwork.py
AdaptivePELE/analysis/plotAdaptive.py
AdaptivePELE/analysis/plotRMSF.py
AdaptivePELE/analysis/plotSpawningClusters.py
AdaptivePELE/analysis/reportSimulation.py
AdaptivePELE/analysis/selectOnPlot.py
AdaptivePELE/analysis/simple_postprocessing.py
AdaptivePELE/analysis/simulationToCsv.py
AdaptivePELE/analysis/splitTrajectory.py
AdaptivePELE/analysis/standarize_MD_energies.py
AdaptivePELE/analysis/trajectory_processing.py
