Metadata-Version: 2.1
Name: AdaptivePELE
Version: 1.7.4
Summary: Enhanced sampling of molecular simulations
Home-page: https://github.com/AdaptivePELE/AdaptivePELE
Author: Daniel Lecina, Joan Francesc Gilabert
Author-email: danilecina@gmail.com, cescgina@gmail.com
Project-URL: Documentation, https://adaptivepele.github.io/AdaptivePELE//
Project-URL: Source, https://github.com/AdaptivePELE/AdaptivePELE
Project-URL: Tracker, https://github.com/AdaptivePELE/AdaptivePELE/issues
Classifier: Programming Language :: Python :: 3
Classifier: Programming Language :: Python :: 2.7
Classifier: License :: OSI Approved :: MIT License
Classifier: Operating System :: POSIX :: Linux
Classifier: Intended Audience :: Science/Research
License-File: LICENSE
